genice/CIF.py
genice/FrankKasper.py
genice/__init__.py
genice/__main__.py
genice/alkyl.py
genice/analice.py
genice/cell.py
genice/digraph.py
genice/genice.py
genice/importer.py
genice/load.py
genice/plugins.py
genice/rigid.py
genice/tool.py
genice/valueparsers.py
genice/formats/_KG.py
genice/formats/__init__.py
genice/formats/_ringstat.py
genice/formats/bdl.py
genice/formats/c.py
genice/formats/cif.py
genice/formats/cif2.py
genice/formats/com.py
genice/formats/d.py
genice/formats/digraph.py
genice/formats/e.py
genice/formats/euler.py
genice/formats/exmol.py
genice/formats/exyz.py
genice/formats/g.py
genice/formats/graph.py
genice/formats/gromacs.py
genice/formats/m.py
genice/formats/mdv_au.py
genice/formats/mdview.py
genice/formats/o.py
genice/formats/openscad.py
genice/formats/p.py
genice/formats/povray.py
genice/formats/python.py
genice/formats/q.py
genice/formats/quaternion.py
genice/formats/r.py
genice/formats/rcom.py
genice/formats/reshape.py
genice/formats/rings.py
genice/formats/towhee.py
genice/formats/xyz.py
genice/formats/y.py
genice/formats/yaplot.py
genice/lattices/0.py
genice/lattices/11.py
genice/lattices/12.py
genice/lattices/13.py
genice/lattices/16.py
genice/lattices/17.py
genice/lattices/1c.py
genice/lattices/1h.py
genice/lattices/1h_unit.py
genice/lattices/2.py
genice/lattices/2D3.py
genice/lattices/2d.py
genice/lattices/3.py
genice/lattices/4.py
genice/lattices/4R.py
genice/lattices/5.py
genice/lattices/5R.py
genice/lattices/6.py
genice/lattices/6h.py
genice/lattices/7.py
genice/lattices/8.py
genice/lattices/9.py
genice/lattices/A.py
genice/lattices/A15.py
genice/lattices/B.py
genice/lattices/C14.py
genice/lattices/C15.py
genice/lattices/C36.py
genice/lattices/CRN1.py
genice/lattices/CRN2.py
genice/lattices/CRN3.py
genice/lattices/CS1.py
genice/lattices/CS2.py
genice/lattices/CS4.py
genice/lattices/DOH.py
genice/lattices/EMT.py
genice/lattices/FAU.py
genice/lattices/FK6layers.py
genice/lattices/FK9layers.py
genice/lattices/HS1.py
GenIce-1.0.11.dist-info/METADATA
GenIce-1.0.11.dist-info/WHEEL
GenIce-1.0.11.dist-info/entry_points.txt
GenIce-1.0.11.dist-info/top_level.txt
GenIce-1.0.11.dist-info/RECORD
