Metadata-Version: 2.1
Name: GenIce
Version: 1.0.11
Summary: A Swiss army knife to generate hydrogen-disordered ice structures.
Home-page: https://github.com/vitroid/GenIce/
Author: Masakazu Matsumoto
Author-email: vitroid@gmail.com
License: MIT
Keywords: genice
Platform: UNKNOWN
Classifier: Development Status :: 4 - Beta
Classifier: Intended Audience :: Developers
Classifier: Programming Language :: Python
Classifier: Programming Language :: Python :: 3.5
Requires-Python: >=3.5
Requires-Dist: networkx (>=2)
Requires-Dist: countrings (>=0.1.7)
Requires-Dist: pairlist (>=0.2.3)
Requires-Dist: yaplotlib (>=0.1)
Requires-Dist: numpy
